CHANGES.txt
CONTRIBUTORS.txt
MANIFEST.in
README.txt
setup.cfg
setup.py
aws/__init__.py
aws.minisite.egg-info/PKG-INFO
aws.minisite.egg-info/SOURCES.txt
aws.minisite.egg-info/dependency_links.txt
aws.minisite.egg-info/entry_points.txt
aws.minisite.egg-info/namespace_packages.txt
aws.minisite.egg-info/not-zip-safe
aws.minisite.egg-info/paster_plugins.txt
aws.minisite.egg-info/requires.txt
aws.minisite.egg-info/top_level.txt
aws/minisite/README.txt
aws/minisite/__init__.py
aws/minisite/config.py
aws/minisite/configure.zcml
aws/minisite/phantasyconfig.py
aws/minisite/setupHandlers.py
aws/minisite/skins.zcml
aws/minisite/browser/__init__.py
aws/minisite/browser/configure.zcml
aws/minisite/browser/phantasy_properties.py
aws/minisite/browser/utils.py
aws/minisite/browser/viewlets.py
aws/minisite/browser/css/minisite.css.dtml
aws/minisite/browser/statics/closelabel.gif
aws/minisite/browser/statics/loading.gif
aws/minisite/browser/statics/minisite.js
aws/minisite/browser/statics/minisite_icon.png
aws/minisite/browser/statics/nextlabel.gif
aws/minisite/browser/statics/photoalbum_icon.png
aws/minisite/browser/statics/prevlabel.gif
aws/minisite/browser/statics/slimbox2.css
aws/minisite/browser/statics/slimbox2.js
aws/minisite/browser/templates/minisite-searchbox.pt
aws/minisite/content/__init__.py
aws/minisite/content/configure.zcml
aws/minisite/content/minisite.py
aws/minisite/content/skin.py
aws/minisite/content/skinschema.py
aws/minisite/data/skin1/body-bg.png
aws/minisite/data/skin1/header-bg.png
aws/minisite/data/skin1/logo.jpg
aws/minisite/data/skin1/logo_aw_solutions.png
aws/minisite/data/skin1/screenshot.jpg
aws/minisite/data/skin1/skin1.css
aws/minisite/data/skin2/body-bg.png
aws/minisite/data/skin2/header-bg.jpg
aws/minisite/data/skin2/logo.jpg
aws/minisite/data/skin2/logo_aw_solutions.png
aws/minisite/data/skin2/portal-bg.png
aws/minisite/data/skin2/screenshot.jpg
aws/minisite/data/skin2/skin2.css
aws/minisite/extendcontents/__init__.py
aws/minisite/extendcontents/configure.zcml
aws/minisite/extendcontents/skinextension.py
aws/minisite/i18n/aws.minisite-fr.po
aws/minisite/i18n/aws.minisite.pot
aws/minisite/interfaces/__init__.py
aws/minisite/interfaces/browserlayer.py
aws/minisite/interfaces/minisite.py
aws/minisite/interfaces/skin.py
aws/minisite/portlets/__init__.py
