Metadata-Version: 1.0
Name: aws.minisite
Version: 1.0.2
Summary: Minimal sites for Plone
Home-page: https://ingeniweb.svn.sourceforge.net/svnroot/ingeniweb/aws.minisite/trunk
Author: Alter Way Solutions
Author-email: support@ingeniweb.com
License: GPL
Keywords: Plone MiniSites
Platform: UNKNOWN
Classifier: Framework :: Plone
Classifier: Programming Language :: Python
Classifier: Topic :: Software Development :: Libraries :: Python Modules
Classifier: License :: OSI Approved :: GNU General Public License (GPL)
